dao/__init__.py
dao/api.py
dao/config.py
dao/errors.py
dao/models.py
daoism-0.0.4.dist-info/METADATA
daoism-0.0.4.dist-info/WHEEL
daoism-0.0.4.dist-info/top_level.txt
daoism-0.0.4.dist-info/RECORD
