Metadata-Version: 2.1
Name: daoism
Version: 0.0.4
Summary: A simple wrapper around Youdao API(WIP)
Home-page: UNKNOWN
Author: Hou
Author-email: hhhoujue@gmail.com
License: MIT
Keywords: ocr,translate,dictionary,youdao
Platform: UNKNOWN
Classifier: License :: OSI Approved :: MIT License
Classifier: Operating System :: OS Independent
Classifier: Programming Language :: Python
Classifier: Programming Language :: Python :: 3
Classifier: Programming Language :: Python :: 3.6
Classifier: Programming Language :: Python :: 3.7
Classifier: Programming Language :: Python :: 3.8
Classifier: Programming Language :: Python :: 3.9
Classifier: Natural Language :: English
Requires-Python: >=3.7
Requires-Dist: httpx
